metabolomics_tools/__init__.py
metabolomics_tools/core.py
metabolomics_tools-0.1.1.dist-info/METADATA
metabolomics_tools-0.1.1.dist-info/WHEEL
metabolomics_tools-0.1.1.dist-info/top_level.txt
metabolomics_tools-0.1.1.dist-info/RECORD
