Metadata-Version: 2.4
Name: metabolomics_tools
Version: 0.1.1
Summary: Tools for preprocessing data for xcms
Author: Amirhossein Sakhteman
Author-email: amirhossein.sakhteman@tume.de
Classifier: Programming Language :: Python :: 3
Classifier: License :: OSI Approved :: MIT License
Requires-Python: >=3.7
Requires-Dist: numpy
Requires-Dist: pandas
Requires-Dist: pubchempy
Dynamic: author
Dynamic: author-email
Dynamic: classifier
Dynamic: description
Dynamic: description-content-type
Dynamic: requires-dist
Dynamic: requires-python
Dynamic: summary
